love_windsurf/__init__.py
love_windsurf/__main__.py
love_windsurf/debug.py
love_windsurf/i18n.py
love_windsurf/py.typed
love_windsurf/server.py
love_windsurf/desktop_app/__init__.py
love_windsurf/desktop_app/desktop_app.py
love_windsurf/desktop_release/__init__.py
love_windsurf/desktop_release/mcp-feedback-enhanced-desktop-linux
love_windsurf/desktop_release/mcp-feedback-enhanced-desktop-macos-arm64
love_windsurf/desktop_release/mcp-feedback-enhanced-desktop-macos-intel
love_windsurf/desktop_release/mcp-feedback-enhanced-desktop.exe
love_windsurf/utils/__init__.py
love_windsurf/utils/error_handler.py
love_windsurf/utils/memory_monitor.py
love_windsurf/utils/resource_manager.py
love_windsurf/web/__init__.py
love_windsurf/web/main.py
love_windsurf/web/constants/__init__.py
love_windsurf/web/constants/message_codes.py
love_windsurf/web/locales/en/translation.json
love_windsurf/web/locales/zh-CN/translation.json
love_windsurf/web/locales/zh-TW/translation.json
love_windsurf/web/models/__init__.py
love_windsurf/web/models/feedback_result.py
love_windsurf/web/models/feedback_session.py
love_windsurf/web/routes/__init__.py
love_windsurf/web/routes/main_routes.py
love_windsurf/web/static/favicon.ico
love_windsurf/web/static/icon-192.png
love_windsurf/web/static/icon.svg
love_windsurf/web/static/index.html
love_windsurf/web/static/css/audio-management.css
love_windsurf/web/static/css/notification-settings.css
love_windsurf/web/static/css/prompt-management.css
love_windsurf/web/static/css/session-management.css
love_windsurf/web/static/css/styles.css
love_windsurf/web/static/js/app.js
love_windsurf/web/static/js/i18n.js
love_windsurf/web/static/js/modules/connection-monitor.js
love_windsurf/web/static/js/modules/file-upload-manager.js
love_windsurf/web/static/js/modules/image-handler.js
love_windsurf/web/static/js/modules/logger.js
love_windsurf/web/static/js/modules/session-manager.js
love_windsurf/web/static/js/modules/settings-manager.js
love_windsurf-2.6.2.dist-info/METADATA
love_windsurf-2.6.2.dist-info/WHEEL
love_windsurf-2.6.2.dist-info/entry_points.txt
love_windsurf-2.6.2.dist-info/licenses/LICENSE
love_windsurf-2.6.2.dist-info/RECORD
